pybin/__init__.py
pybin/__main__.py
pybin/cli.py
pybin/core.py
pybin-0.3.4.dist-info/DESCRIPTION.rst
pybin-0.3.4.dist-info/METADATA
pybin-0.3.4.dist-info/RECORD
pybin-0.3.4.dist-info/WHEEL
pybin-0.3.4.dist-info/entry_points.txt
pybin-0.3.4.dist-info/metadata.json
pybin-0.3.4.dist-info/top_level.txt
tests/__init__.py
