Metadata-Version: 2.0
Name: pybin
Version: 0.3.4
Summary: Cross-platform tool to put Python's user bin in PATH, no sudo/runas required!
Home-page: https://github.com/ofek/pybin
Author: Ofek Lev
Author-email: ofekmeister@gmail.com
License: MIT/Apache-2.0
Download-URL: https://github.com/ofek/pybin
Keywords: packaging,scripts,user path,path,cli
Platform: UNKNOWN
Classifier: Development Status :: 4 - Beta
Classifier: Intended Audience :: Developers
Classifier: License :: OSI Approved :: MIT License
Classifier: License :: OSI Approved :: Apache Software License
Classifier: Natural Language :: English
Classifier: Operating System :: OS Independent
Classifier: Programming Language :: Python :: 2.6
Classifier: Programming Language :: Python :: 2.7
Classifier: Programming Language :: Python :: 3.3
Classifier: Programming Language :: Python :: 3.4
Classifier: Programming Language :: Python :: 3.5
Classifier: Programming Language :: Python :: 3.6
Classifier: Programming Language :: Python :: Implementation :: CPython
Classifier: Programming Language :: Python :: Implementation :: PyPy
Requires-Dist: click
